setup.py
test/test_import.py
test/test_parse.py
thrustcurve/__init__.py
thrustcurve.egg-info/PKG-INFO
thrustcurve.egg-info/SOURCES.txt
thrustcurve.egg-info/dependency_links.txt
thrustcurve.egg-info/requires.txt
thrustcurve.egg-info/top_level.txt