Metadata-Version: 1.0
Name: thrustcurve
Version: 0.1.0
Summary: Parse engine thrust curve files for amateur rocketry
Home-page: https://github.com/rjw57/thrustcurve
Author: Rich Wareham
Author-email: rich.thrustcurve@richwareham.com
License: UNKNOWN
Platform: UNKNOWN
